README.md
setup.cfg
setup.py
nce/__init__.py
nce/alias_multinomial.py
nce/index_gru.py
nce/index_linear.py
nce/nce_loss.py
pytorch_nce.egg-info/PKG-INFO
pytorch_nce.egg-info/SOURCES.txt
pytorch_nce.egg-info/dependency_links.txt
pytorch_nce.egg-info/requires.txt
pytorch_nce.egg-info/top_level.txt
test/test_evaluation.py
test/test_perplexity.py