Metadata-Version: 2.1
Name: pytorch-nce
Version: 0.0.1
Summary: An NCE implementation in pytorch
Home-page: https://github.com/Stonesjtu/Pytorch-NCE
Author: Kaiyu Shi
Author-email: skyisno.1@gmail.com
License: UNKNOWN
Platform: UNKNOWN
Classifier: License :: OSI Approved :: MIT License
Classifier: Operating System :: OS Independent
